tflite2tensorflow/__init__.py
tflite2tensorflow/mediapipeCustomOp.py
tflite2tensorflow/tflite2tensorflow.py
tflite2tensorflow/view_npy.py
tflite2tensorflow-1.22.0.data/scripts/tflite2tensorflow
tflite2tensorflow-1.22.0.data/scripts/view_npy
tflite2tensorflow-1.22.0.dist-info/LICENSE
tflite2tensorflow-1.22.0.dist-info/METADATA
tflite2tensorflow-1.22.0.dist-info/WHEEL
tflite2tensorflow-1.22.0.dist-info/top_level.txt
tflite2tensorflow-1.22.0.dist-info/RECORD
