Metadata-Version: 2.1
Name: tflite2tensorflow
Version: 1.22.0
Summary: Generate saved_model, tfjs, tf-trt, EdgeTPU, CoreML, quantized tflite, ONNX, OpenVINO, Myriad Inference Engine blob and .pb from .tflite.
Home-page: https://github.com/PINTO0309/tflite2tensorflow
Author: Katsuya Hyodo
Author-email: rmsdh122@yahoo.co.jp
License: MIT License
Platform: linux
Platform: unix
Requires-Python: >3.6
License-File: LICENSE
